{
    "id": "hvezda-na-vrbe-olympic",
    "title": "Hvězda na vrbě",
    "artist": [],
    "band": [
        "Olympic"
    ],
    "originalKey": "Am",
    "capo": 0,
    "lyrics": [
        {
            "block_start": true,
            "chords": "           Ami   Emi    Ami   F       Emi   G7 C Emi",
            "text": "1. Kdo se večer hájem vrací, ten ať klopí zraky,"
        },
        {
            "chords": "   G      Ami   Emi Ami Dmi  G7  Emi E A C Emi",
            "text": "   ať je nikdy neobrací k vrbě křivolaký,"
        },
        {
            "chords": "    G     Ami Emi   Ami   F       Emi   G7 C Emi",
            "text": "   jinak jeho oči zjistí, i když se to nezdá,"
        },
        {
            "chords": "          Ami   Emi  Ami   Dmi  F        Ami",
            "text": "   že na vrbě kromě listí visí malá hvězda."
        },
        {
            "block_start": true,
            "chords": "        C                F             C           F",
            "text": "R: Viděli jsme jednou v lukách plakat na té vrbě kluka,"
        },
        {
            "chords": "          Dmi         Bb7         D7             G7 Emi G",
            "text": "   který pevně věřil tomu, že ji sundá z toho stromu."
        },
        {
            "block_start": true,
            "chords": "",
            "text": "2. Kdo o hvězdy jeví zájem, zem když večer chladne,"
        },
        {
            "chords": "",
            "text": "   ať jde klidně přesto hájem, hvězda někdy spadne,"
        },
        {
            "chords": "",
            "text": "   ať se pro ni rosou brodí a pak vrbu najde si"
        },
        {
            "chords": "",
            "text": "   a pro ty, co kolem chodí, na tu větev zavěsí."
        },
        {
            "block_start": true,
            "chords": "",
            "text": "R:"
        }
    ]
}