{
    "id": "man-of-constant-sorrow-soggy-bottom-boys",
    "title": "Man Of Constant Sorrow",
    "artist": [],
    "band": [
        "Soggy Bottom Boys"
    ],
    "originalKey": "D",
    "capo": 3,
    "lyrics": [
        {
            "chords": "D             A                       D",
            "text": "In constant sorrow all through his days"
        },
        {
            "chords": "    D                       G",
            "text": "1. I Am A Man Of Constant Sorrow"
        },
        {
            "chords": "              A                D",
            "text": "   I‘ve seen trouble all my day."
        },
        {
            "chords": "                             G",
            "text": "   I bid farewell to old Kentucky"
        },
        {
            "chords": "               A                       D",
            "text": "   The place where I was born and raised."
        },
        {
            "chords": "               A                       D",
            "text": "   The place where he was born and raised"
        },
        {
            "chords": "",
            "text": "2. For six long years I‘ve been in trouble"
        },
        {
            "chords": "",
            "text": "   No pleasures here on earth I found"
        },
        {
            "chords": "",
            "text": "   For in this world I‘m bound to ramble"
        },
        {
            "chords": "",
            "text": "   I have no friends to help me now."
        },
        {
            "chords": "",
            "text": "   He has no friends to help him now"
        },
        {
            "chords": "",
            "text": "3. It‘s fare thee well my old lover"
        },
        {
            "chords": "",
            "text": "   I never expect to see you again"
        },
        {
            "chords": "",
            "text": "   For I‘m bound to ride that northern railroad"
        },
        {
            "chords": "",
            "text": "   Perhaps I‘ll die upon this train."
        },
        {
            "chords": "",
            "text": "   Perhaps he‘ll die upon this train."
        },
        {
            "chords": "",
            "text": "4. You can bury me in some deep valley"
        },
        {
            "chords": "",
            "text": "   For many years where I may lay"
        },
        {
            "chords": "",
            "text": "   Then you may learn to love another"
        },
        {
            "chords": "",
            "text": "   While I am sleeping in my grave."
        },
        {
            "chords": "",
            "text": "   While he is sleeping in his grave."
        },
        {
            "chords": "",
            "text": "5. Maybe your friends think I‘m just a stranger"
        },
        {
            "chords": "",
            "text": "   My face you‘ll never see no more."
        },
        {
            "chords": "",
            "text": "   But there is one promise that is given"
        },
        {
            "chords": "",
            "text": "   I‘ll meet you on God‘s golden shore."
        },
        {
            "chords": "",
            "text": "   He‘ll meet you on God‘s golden shore.."
        }
    ]
}