{
    "id": "nahy-richard-m-ller",
    "title": "Nahý",
    "artist": [
        "Richard Müller"
    ],
    "band": [],
    "originalKey": "C",
    "capo": 0,
    "lyrics": [
        {
            "chords": "G D G D G D G D",
            "text": ""
        },
        {
            "chords": "C                 D     G",
            "text": "Ublížil som ženám deťom mamám"
        },
        {
            "chords": "C     D           G",
            "text": "Svoju hlbokú úctu skladám"
        },
        {
            "chords": "C    D         Emi",
            "text": "Pred vami moji drahí"
        },
        {
            "chords": "       C            D  C",
            "text": "Ktorým zneuctil som    prahy"
        },
        {
            "chords": "C  D              G",
            "text": "Od Hlohovca až do Prahy"
        },
        {
            "chords": "C  D   G",
            "text": "   som nahý"
        },
        {
            "chords": "C       D               Emi",
            "text": "Nech mi všetci svätí pomôžu"
        },
        {
            "chords": "C    D       C",
            "text": "nahý až na kožu"
        },
        {
            "chords": "   G  D       Emi",
            "text": "R: Už nebudem nahý"
        },
        {
            "chords": "         C            G",
            "text": "   Drahé slečny drahé ženy"
        },
        {
            "chords": "   D           Emi",
            "text": "   Od teraz až navždy"
        },
        {
            "chords": "            C",
            "text": "   zostávam oblečený"
        },
        {
            "chords": "   G   D         Emi",
            "text": "   Neverím že mi pomôžu"
        },
        {
            "chords": "   C        D       C",
            "text": "   som nahý až na kožu"
        },
        {
            "chords": "C              D",
            "text": "Nahý už som bol"
        },
        {
            "chords": "G",
            "text": "stačí"
        },
        {
            "chords": "C        D            G   CDEmi",
            "text": "Normálne na egy keto három"
        },
        {
            "chords": "C              D   C",
            "text": "nevyzlečiem sa ani pred lekárom"
        }
    ]
}